ya360/__init__.py
ya360/__main__.py
ya360/antispam.py
ya360/cmd.py
ya360/configure.py
ya360/departments.py
ya360/groups.py
ya360/logs.py
ya360/mail.py
ya360/routing.py
ya360/tid.py
ya360/tools.py
ya360/users.py
ya360/whois.py
ya360-3.6.2.dist-info/LICENSE
ya360-3.6.2.dist-info/METADATA
ya360-3.6.2.dist-info/WHEEL
ya360-3.6.2.dist-info/entry_points.txt
ya360-3.6.2.dist-info/top_level.txt
ya360-3.6.2.dist-info/RECORD
