Metadata-Version: 2.1
Name: ya360
Version: 3.6.2
Summary: Утилита командной строки для Yandex 360
Author-email: Купцов Игорь <ya360@uh.net.ru>
License: MIT
Project-URL: Homepage, https://ya360.uh.net.ru
Project-URL: Bug Tracker, https://github.com/imercury13/ya360/issues
Project-URL: Documentation, https://ya360.readthedocs.io/
Project-URL: Download, https://github.com/imercury13/ya360
Keywords: yandex,yandex360
Classifier: Operating System :: MacOS :: MacOS X
Classifier: Operating System :: Microsoft :: Windows
Classifier: Operating System :: POSIX
Classifier: Programming Language :: Python
Classifier: Environment :: Console
Classifier: Intended Audience :: System Administrators
Requires-Python: >=3.6.9
License-File: LICENSE
Requires-Dist: yandex-oauth >=1.1.2
Requires-Dist: yandex-360 >=2.2.1
